mostlyai/__init__.py
mostly_python-0.0.1.dist-info/LICENSE
mostly_python-0.0.1.dist-info/METADATA
mostly_python-0.0.1.dist-info/WHEEL
mostly_python-0.0.1.dist-info/top_level.txt
mostly_python-0.0.1.dist-info/RECORD
