Metadata-Version: 2.1
Name: mostly-python
Version: 0.0.1
Summary: The official Python library for the mostlyai API
Author-email: MostlyAI <office@mostly.ai>
License: Apache License
Project-URL: Home, https://github.com/mostly-ai/mostly-python
Requires-Python: >=3.6
License-File: LICENSE
